calculate_total_bill/__init__.py
calculate_total_bill/bill.py
calculate_total_bill-0.2.1.dist-info/licenses/LICENSE
calculate_total_bill-0.2.1.dist-info/METADATA
calculate_total_bill-0.2.1.dist-info/WHEEL
calculate_total_bill-0.2.1.dist-info/top_level.txt
calculate_total_bill-0.2.1.dist-info/RECORD
