Metadata-Version: 2.4
Name: calculate_total_bill
Version: 0.2.1
Summary: This is a simple Python package that calculates total bill amount.
Home-page: 
Author: Gopi
Author-email:  x23306882@student.ncirl.ie
Keywords: calculate_total_bill
Classifier: Intended Audience :: Education
Classifier: Operating System :: Microsoft :: Windows :: Windows 10
Classifier: License :: OSI Approved :: MIT License
Classifier: Programming Language :: Python :: 3
Requires-Python: >=3.6
License-File: LICENSE
Dynamic: author
Dynamic: author-email
Dynamic: classifier
Dynamic: description
Dynamic: keywords
Dynamic: license-file
Dynamic: requires-python
Dynamic: summary
